postgrespy/__init__.py
postgrespy/db.py
postgrespy/fields.py
postgrespy/models.py
postgrespy/queries.py
postgrespy-0.3.1.dist-info/DESCRIPTION.rst
postgrespy-0.3.1.dist-info/METADATA
postgrespy-0.3.1.dist-info/RECORD
postgrespy-0.3.1.dist-info/WHEEL
postgrespy-0.3.1.dist-info/metadata.json
postgrespy-0.3.1.dist-info/top_level.txt
