Metadata-Version: 2.0
Name: postgrespy
Version: 0.3.1
Summary: A simple postgres orm
Home-page: https://github.com/nguyendv/postgrespy
Author: Dung (Dave) Nguyen
Author-email: dvnguyen.vn@gmail.com
License: UNKNOWN
Download-URL: https://github.com/nguyendv/postgrespy/archive/0.3.1.tar.gz
Platform: UNKNOWN
Requires-Python: ~=3.6
Requires-Dist: psycopg2 (>=2.7)
Requires-Dist: Jinja2 (>=2.9)
